gaussian_splatting/__init__.py
gaussian_splatting/camera.py
gaussian_splatting/camera_trainable.py
gaussian_splatting/gaussian_model.py
gaussian_splatting/prepare.py
gaussian_splatting/render.py
gaussian_splatting/train.py
gaussian_splatting/dataset/__init__.py
gaussian_splatting/dataset/camera_trainable.py
gaussian_splatting/dataset/dataset.py
gaussian_splatting/dataset/colmap/__init__.py
gaussian_splatting/dataset/colmap/dataset.py
gaussian_splatting/dataset/colmap/params_init.py
gaussian_splatting/dataset/colmap/read_write_model.py
gaussian_splatting/diff_gaussian_rasterization/_C.cpython-310-x86_64-linux-gnu.so
gaussian_splatting/diff_gaussian_rasterization/__init__.py
gaussian_splatting/simple_knn/_C.cpython-310-x86_64-linux-gnu.so
gaussian_splatting/trainer/__init__.py
gaussian_splatting/trainer/abc.py
gaussian_splatting/trainer/base.py
gaussian_splatting/trainer/camera_trainable.py
gaussian_splatting/trainer/combinations.py
gaussian_splatting/trainer/depth.py
gaussian_splatting/trainer/opacity_reset.py
gaussian_splatting/trainer/sh_lift.py
gaussian_splatting/trainer/densifier/__init__.py
gaussian_splatting/trainer/densifier/abc.py
gaussian_splatting/trainer/densifier/adaptive.py
gaussian_splatting/trainer/densifier/combinations.py
gaussian_splatting/trainer/densifier/densifier.py
gaussian_splatting/trainer/densifier/pruner.py
gaussian_splatting/trainer/densifier/trainer.py
gaussian_splatting/trainer/extensions/__init__.py
gaussian_splatting/trainer/extensions/scale_reg.py
gaussian_splatting/utils/__init__.py
gaussian_splatting/utils/general.py
gaussian_splatting/utils/graphics.py
gaussian_splatting/utils/loss.py
gaussian_splatting/utils/metrics.py
gaussian_splatting/utils/pose.py
gaussian_splatting/utils/schedular.py
gaussian_splatting/utils/shs.py
gaussian_splatting/utils/unproject.py
gaussian_splatting/utils/lpipsPyTorch/__init__.py
gaussian_splatting/utils/lpipsPyTorch/modules/__init__.py
gaussian_splatting-1.20.6.dist-info/LICENSE.md
gaussian_splatting-1.20.6.dist-info/METADATA
gaussian_splatting-1.20.6.dist-info/WHEEL
gaussian_splatting-1.20.6.dist-info/top_level.txt
gaussian_splatting-1.20.6.dist-info/RECORD
gaussian_splatting-1.20.6.dist-info/sboms/auditwheel.cdx.json
