Metadata-Version: 2.1
Name: gaussian_splatting
Version: 1.20.6
Summary: Refactored python training and inference code for 3D Gaussian Splatting
Home-page: https://github.com/yindaheng98/gaussian-splatting
Author: yindaheng98
Author-email: yindaheng98@gmail.com
Classifier: Programming Language :: Python :: 3
License-File: LICENSE.md
Requires-Dist: torch
Requires-Dist: torchvision
Requires-Dist: tqdm
Requires-Dist: plyfile
Requires-Dist: tifffile
Requires-Dist: numpy
Requires-Dist: opencv-python
Requires-Dist: pillow
Requires-Dist: open3d
